template_analysis/__init__.py
template_analysis/_version.py
template_analysis/analyzer.py
template_analysis/symbol.py
template_analysis/template.py
template_analysis-0.0.7.dist-info/LICENSE
template_analysis-0.0.7.dist-info/METADATA
template_analysis-0.0.7.dist-info/WHEEL
template_analysis-0.0.7.dist-info/top_level.txt
template_analysis-0.0.7.dist-info/RECORD
