Metadata-Version: 2.1
Name: template_analysis
Version: 0.0.7
Summary: Create template from strings (reverse formatter)
Home-page: https://github.com/kitsuyui/python-template-analysis
Author: Yui Kitsu
Author-email: kitsuyui+github@kitsuyui.com
License: BSD-3-Clause
Classifier: Development Status :: 3 - Alpha
Classifier: License :: OSI Approved :: BSD License
Classifier: Programming Language :: Python :: 3.9
Classifier: Programming Language :: Python :: 3.10
Classifier: Programming Language :: Python :: 3.11
Classifier: Programming Language :: Python :: 3.12
Classifier: Programming Language :: Python :: 3.13
Classifier: Intended Audience :: Developers
Classifier: Topic :: Software Development :: Libraries
Requires-Python: >=3.9
License-File: LICENSE
